[
  {
    "ContainingType": "EmployeeFilterDemo.Controllers.EmployeeController",
    "Method": "AddEmployee",
    "RelativePath": "api/Employee",
    "HttpMethod": "POST",
    "IsController": true,
    "Order": 0,
    "Parameters": [
      {
        "Name": "employee",
        "Type": "EmployeeFilterDemo.Models.Employee",
        "IsRequired": true
      }
    ],
    "ReturnTypes": []
  },
  {
    "ContainingType": "EmployeeFilterDemo.Controllers.EmployeeController",
    "Method": "GetStandard",
    "RelativePath": "api/Employee/standard",
    "HttpMethod": "GET",
    "IsController": true,
    "Order": 0,
    "Parameters": [],
    "ReturnTypes": [
      {
        "Type": "System.Collections.Generic.List\u00601[[EmployeeFilterDemo.Models.Employee, EmployeeFilterDemo, Version=1.0.0.0, Culture=neutral, PublicKeyToken=null]]",
        "MediaTypes": [
          "text/plain",
          "application/json",
          "text/json"
        ],
        "StatusCode": 200
      },
      {
        "Type": "System.Void",
        "MediaTypes": [],
        "StatusCode": 500
      }
    ]
  },
  {
    "ContainingType": "EmployeeFilterDemo.Controllers.WeatherForecastController",
    "Method": "Get",
    "RelativePath": "WeatherForecast",
    "HttpMethod": "GET",
    "IsController": true,
    "Order": 0,
    "Parameters": [],
    "ReturnTypes": [
      {
        "Type": "System.Collections.Generic.IEnumerable\u00601[[EmployeeFilterDemo.WeatherForecast, EmployeeFilterDemo, Version=1.0.0.0, Culture=neutral, PublicKeyToken=null]]",
        "MediaTypes": [
          "text/plain",
          "application/json",
          "text/json"
        ],
        "StatusCode": 200
      }
    ],
    "EndpointName": "GetWeatherForecast"
  }
]